doceasy.py
doceasy-0.4.0.dist-info/LICENSE
doceasy-0.4.0.dist-info/METADATA
doceasy-0.4.0.dist-info/WHEEL
doceasy-0.4.0.dist-info/top_level.txt
doceasy-0.4.0.dist-info/RECORD
