Metadata-Version: 2.1
Name: doceasy
Version: 0.4.0
Summary: Wrapper around docopt and schema
Home-page: https://github.com/jpcsmith/doceasy
Author: Jean-Pierre Smith
Author-email: rougesprit@gmail.com
License: UNKNOWN
Platform: UNKNOWN
Classifier: Programming Language :: Python :: 3
Classifier: License :: OSI Approved :: MIT License
Classifier: Operating System :: OS Independent
Requires-Python: >=3.5
Requires-Dist: docopt
Requires-Dist: schema
Provides-Extra: dev
Requires-Dist: flake8 ; extra == 'dev'
Requires-Dist: mypy ; extra == 'dev'
Requires-Dist: pylint ; extra == 'dev'
Provides-Extra: test
Requires-Dist: pytest ; extra == 'test'
